droblo/__init__.py
droblo/droblo_reports.py
droblo/droblod.py
droblo/ORM/__init__.py
droblo/ORM/droblo_ORM.py
droblo/ORM/droblo_reports_ORM.py
droblo/data/Droblod.xml
droblo/data/droblod.plist
droblo/data/droblod.user.service
droblo/filesystem/__init__.py
droblo/filesystem/droblo_fs.py
droblo/postgreSQL_poller/__init__.py
droblo/postgreSQL_poller/drobloPostgreSQLPoller.py
droblo-0.0.9.dist-info/LICENSE.txt
droblo-0.0.9.dist-info/METADATA
droblo-0.0.9.dist-info/WHEEL
droblo-0.0.9.dist-info/top_level.txt
droblo-0.0.9.dist-info/RECORD
