Metadata-Version: 2.1
Name: droblo
Version: 0.0.9
Summary: A multi-hosts, PostgreSQL backed, filesystem duplication detection system.
Home-page: https://github.com/KurisuD/droblo
Author: KurisuD
Author-email: KurisuD@pypi.darnand.net
License: UNKNOWN
Platform: UNKNOWN
Classifier: Development Status :: 3 - Alpha
Classifier: Programming Language :: Python :: 3 :: Only
Classifier: Programming Language :: Python :: 3.5
Classifier: Intended Audience :: End Users/Desktop
Classifier: License :: OSI Approved :: GNU Affero General Public License v3 or later (AGPLv3+)
Classifier: Operating System :: OS Independent
Classifier: Topic :: Utilities
Classifier: Topic :: System :: Filesystems
Requires-Python: >=3.5
Requires-Dist: pap-logger
Requires-Dist: watchdog
Requires-Dist: pathlib
Requires-Dist: psycopg2-binary
Requires-Dist: SQLAlchemy
